uswarm/__init__.py
uswarm/aio_map.py
uswarm/cli.py
uswarm/definitions.py
uswarm/fs.py
uswarm/hsync.py
uswarm/http.py
uswarm/kernel.py
uswarm/kernel_async_old.py
uswarm/kernel_hide.py
uswarm/network.py
uswarm/parsers.py
uswarm/pools.py
uswarm/reactor.py
uswarm/rexp.py
uswarm/sparse.py
uswarm/sparse_old.py
uswarm/tools.py
uswarm/uobjects.py
uswarm/uswarm.py
uswarm/workflow.py
uswarm/kernel/__init__.py
uswarm/kernel/channel.py
uswarm/kernel/demo.py
uswarm/kernel/dom.py
uswarm/kernel/http.py
uswarm/kernel/kernel.py
uswarm/kernel/kernel_old.py
uswarm/kernel/kurio.py
uswarm/kernel/node.py
uswarm/kernel/old.py
uswarm/kernel/pacing.py
uswarm/kernel/pool.py
uswarm/kernel/request.py
uswarm/kernel/select_kernel.py
uswarm/kernel/stats.py
uswarm/kernel/stm.py
uswarm/kernel/userver.py
uswarm/kurio/__init__.py
uswarm/kurio/helpers.py
uswarm/kurio/kernel.py
uswarm/kurio/kurio.py
uswarm/kurio/pubsub.py
uswarm/kurio/resource.py
uswarm/kurio/sync.py
uswarm/tools/__init__.py
uswarm/tools/abc.py
uswarm/tools/any.py
uswarm/tools/calls.py
uswarm/tools/colors.py
uswarm/tools/configurations.py
uswarm/tools/containers.py
uswarm/tools/converters.py
uswarm/tools/dataframes.py
uswarm/tools/factory.py
uswarm/tools/files.py
uswarm/tools/financial.py
uswarm/tools/financial_org.py
uswarm/tools/fractal.py
uswarm/tools/grid.py
uswarm/tools/iterators.py
uswarm/tools/lexers.py
uswarm/tools/logs.py
uswarm/tools/metrics.py
uswarm/tools/plots.py
uswarm/tools/progress.py
uswarm/tools/pubsub.py
uswarm/tools/rand.py
uswarm/tools/selenium.py
uswarm/tools/stats.py
uswarm/tools/stream.py
uswarm/tools/system.py
uswarm/tools/tabula.py
uswarm/tools/templates.py
uswarm/tools/testing.py
uswarm/tools/units.py
uswarm/tools/webhelpers.py
uswarm/tools/webtools.py
uswarm-0.1.1.dist-info/AUTHORS.rst
uswarm-0.1.1.dist-info/LICENSE
uswarm-0.1.1.dist-info/METADATA
uswarm-0.1.1.dist-info/WHEEL
uswarm-0.1.1.dist-info/entry_points.txt
uswarm-0.1.1.dist-info/top_level.txt
uswarm-0.1.1.dist-info/RECORD
