Metadata-Version: 2.1
Name: uswarm
Version: 0.1.1
Summary: U-Swarm
Home-page: https://github.com/asterio.gonzalez/uswarm
Author: Asterio
Author-email: asterio@protonmail.com
Keywords: uswarm
Classifier: Development Status :: 2 - Pre-Alpha
Classifier: Intended Audience :: Developers
Classifier: Natural Language :: English
Classifier: Programming Language :: Python :: 3.8
Classifier: Programming Language :: Python :: 3.9
Requires-Python: >=3.6
License-File: LICENSE
License-File: AUTHORS.rst
Requires-Dist: async-timeout
Requires-Dist: codenamize
Requires-Dist: compressedlogger
Requires-Dist: pandas
Requires-Dist: python-datemath
Requires-Dist: selenium
Requires-Dist: tk
Requires-Dist: black
Requires-Dist: openpyxl
Requires-Dist: glom
